jupikchr/__init__.py
jupikchr/_version.py
jupikchr/widget.py
jupikchr/_d/share/jupyter/labextensions/@deathbeds/jupikchr/package.json
jupikchr/_d/share/jupyter/labextensions/@deathbeds/jupikchr/schemas/@deathbeds/jupikchr/package.json.orig
jupikchr/_d/share/jupyter/labextensions/@deathbeds/jupikchr/static/247.13abfeca9a0f37225518.js
jupikchr/_d/share/jupyter/labextensions/@deathbeds/jupikchr/static/247.13abfeca9a0f37225518.js.map
jupikchr/_d/share/jupyter/labextensions/@deathbeds/jupikchr/static/26.f6a4da25e0f8c01fad42.js
jupikchr/_d/share/jupyter/labextensions/@deathbeds/jupikchr/static/26.f6a4da25e0f8c01fad42.js.map
jupikchr/_d/share/jupyter/labextensions/@deathbeds/jupikchr/static/346.5a03066a604b4d261258.js
jupikchr/_d/share/jupyter/labextensions/@deathbeds/jupikchr/static/346.5a03066a604b4d261258.js.map
jupikchr/_d/share/jupyter/labextensions/@deathbeds/jupikchr/static/458.574dfc8f4184872a1c24.js
jupikchr/_d/share/jupyter/labextensions/@deathbeds/jupikchr/static/458.574dfc8f4184872a1c24.js.map
jupikchr/_d/share/jupyter/labextensions/@deathbeds/jupikchr/static/809.60630464cf132fc93e32.js
jupikchr/_d/share/jupyter/labextensions/@deathbeds/jupikchr/static/809.60630464cf132fc93e32.js.map
jupikchr/_d/share/jupyter/labextensions/@deathbeds/jupikchr/static/91.01fe2905b93d776b922d.js
jupikchr/_d/share/jupyter/labextensions/@deathbeds/jupikchr/static/91.01fe2905b93d776b922d.js.map
jupikchr/_d/share/jupyter/labextensions/@deathbeds/jupikchr/static/remoteEntry.9adeb02fc071a64e606b.js
jupikchr/_d/share/jupyter/labextensions/@deathbeds/jupikchr/static/remoteEntry.9adeb02fc071a64e606b.js.map
jupikchr/_d/share/jupyter/labextensions/@deathbeds/jupikchr/static/third-party-licenses.json
jupikchr/_d/share/jupyter/labextensions/@deathbeds/jupikchr/static/vendor/fossil-pikchr/pikchr-worker.js
jupikchr/_d/share/jupyter/labextensions/@deathbeds/jupikchr/static/vendor/fossil-pikchr/pikchr.js
jupikchr-0.2.0.dist-info/LICENSE.txt
jupikchr-0.2.0.dist-info/WHEEL
jupikchr-0.2.0.dist-info/METADATA
jupikchr-0.2.0.dist-info/RECORD
