Metadata-Version: 2.1
Name: jupikchr
Version: 0.2.0
Summary: pikchr text-based diagrams for JupyterLab, etc.
Author-email: jupikchr contributors <deathbeds@googlegroups.com>
Requires-Python: >=3.7
Classifier: Framework :: Jupyter :: JupyterLab :: 3
Classifier: Framework :: Jupyter :: JupyterLab :: Extensions :: Prebuilt
Classifier: Framework :: Jupyter :: JupyterLab :: Extensions
Classifier: Framework :: Jupyter :: JupyterLab
Classifier: Framework :: Jupyter
Classifier: License :: OSI Approved :: BSD License
Classifier: Programming Language :: Python :: 3 :: Only
Classifier: Programming Language :: Python :: 3
Requires-Dist: ipywidgets >=7,<9
Requires-Dist: jupyterlab-markup >=2.0.0
Project-URL: Bug Tracker, https://github.com/deathbeds/jupikchr/issues
Project-URL: Changelog, https://github.com/deathbeds/jupikchr/blob/main/CHANGELOG.md
Project-URL: Documentation, https://jupikchr.rtfd.io
Project-URL: Source, https://github.com/deathbeds/jupikchr
